audiotsm2/__init__.py
audiotsm2/ola.py
audiotsm2/phasevocoder.py
audiotsm2/wsola.py
audiotsm2/base/__init__.py
audiotsm2/base/analysis_synthesis.py
audiotsm2/base/tsm.py
audiotsm2/io/__init__.py
audiotsm2/io/array.py
audiotsm2/io/stream.py
audiotsm2/io/wav.py
audiotsm2/utils/__init__.py
audiotsm2/utils/cbuffer.py
audiotsm2/utils/normalizebuffer.py
audiotsm2/utils/windows.py
audiotsm2-0.2.1.dist-info/LICENSE
audiotsm2-0.2.1.dist-info/METADATA
audiotsm2-0.2.1.dist-info/WHEEL
audiotsm2-0.2.1.dist-info/top_level.txt
audiotsm2-0.2.1.dist-info/RECORD
