Metadata-Version: 2.1
Name: audiotsm2
Version: 0.2.1
Summary: A real-time audio time-scale modification library
Home-page: https://github.com/WyattBlue/audiotsm2
Author: WyattBlue
Author-email: wyattbluesandbox@gmail.com
License: MIT
Platform: UNKNOWN
Classifier: Intended Audience :: Developers
Classifier: License :: OSI Approved :: MIT License
Classifier: Programming Language :: Python
Classifier: Programming Language :: Python :: 3
Classifier: Programming Language :: Python :: 3.4
Classifier: Programming Language :: Python :: 3.5
Classifier: Programming Language :: Python :: 3.6
Classifier: Programming Language :: Python :: 3.7
Classifier: Programming Language :: Python :: 3.8
Classifier: Programming Language :: Python :: Implementation :: CPython
Classifier: Programming Language :: Python :: Implementation :: PyPy
Requires-Dist: numpy
